easydubins/__init__.py
easydubins/__main__.py
easydubins/config.cfg
easydubins/dubin_path.py
easydubins-1.3.1.dist-info/LICENSE
easydubins-1.3.1.dist-info/METADATA
easydubins-1.3.1.dist-info/WHEEL
easydubins-1.3.1.dist-info/entry_points.txt
easydubins-1.3.1.dist-info/top_level.txt
easydubins-1.3.1.dist-info/RECORD
