Metadata-Version: 2.1
Name: easydubins
Version: 1.3.1
Summary: To generate dubin curves projection points.
Home-page: https://github.com/rsrishav/easydubins
Author: Rishav
Author-email: rsrishav0@gmail.com
License: GPL3
Platform: UNKNOWN
Classifier: Programming Language :: Python
Classifier: Programming Language :: Python :: 2
Classifier: Programming Language :: Python :: 3
Classifier: Operating System :: OS Independent
Requires-Dist: importlib-resources
